icetrackpy/icetrackpy_functions.cpython-39-x86_64-linux-gnu.so
icetrackpy-0.0.4.dist-info/RECORD
icetrackpy-0.0.4.dist-info/top_level.txt
icetrackpy-0.0.4.dist-info/METADATA
icetrackpy-0.0.4.dist-info/WHEEL
icetrackpy-0.0.4.dist-info/LICENSE
icetrackpy.libs/libgfortran-b077a895.so.5.0.0
icetrackpy.libs/libquadmath-bb8b391f.so.0.0.0
icetrackpy.libs/libopenblasp-r0-0e83b514.3.27.so
