Metadata-Version: 2.1
Name: icetrackpy
Version: 0.0.4
Summary: Tools to work on output from Elmer ice flow simulation
Home-page: https://gricad-gitlab.univ-grenoble-alpes.fr/mecaiceige/tools/lib_python/icetrackpy
Author: Martin Thiriet
Author-email: martin.thiriet1@gmail.com
License: GPL-3.0
Classifier: Intended Audience :: Science/Research
Classifier: License :: OSI Approved :: GNU General Public License v3 (GPLv3)
Classifier: Operating System :: OS Independent
Classifier: Programming Language :: Python :: 3 :: Only
Classifier: Programming Language :: C
Requires-Python: >=3.8
License-File: LICENSE
Requires-Dist: meshio
Requires-Dist: numpy
Requires-Dist: matplotlib
Requires-Dist: vispy
Requires-Dist: scipy
